skmCalc/__init__.py
skmCalc-0.1.dist-info/METADATA
skmCalc-0.1.dist-info/WHEEL
skmCalc-0.1.dist-info/licence.txt
skmCalc-0.1.dist-info/top_level.txt
skmCalc-0.1.dist-info/RECORD
