Metadata-Version: 2.1
Name: skmCalc
Version: 0.1
Summary: simple calculator
Home-page: UNKNOWN
Author: Sumit Kumar Mishra
Author-email: UNKNOWN
License: UNKNOWN
Platform: UNKNOWN
